n8n_lint/__init__.py
n8n_lint/__main__.py
n8n_lint/utils.py
n8n_lint/cli/__init__.py
n8n_lint/cli/main.py
n8n_lint/core/__init__.py
n8n_lint/core/errors.py
n8n_lint/core/logger.py
n8n_lint/core/validator.py
n8n_lint/formatters/__init__.py
n8n_lint/formatters/base.py
n8n_lint/formatters/console.py
n8n_lint/formatters/html.py
n8n_lint/formatters/json.py
n8n_lint/formatters/markdown.py
n8n_lint/schemas/__init__.py
n8n_lint/utils/__init__.py
n8n_lint/utils/progress.py
n8n_lint-1.1.2.dist-info/licenses/LICENSE
n8n_lint-1.1.2.dist-info/METADATA
n8n_lint-1.1.2.dist-info/WHEEL
n8n_lint-1.1.2.dist-info/entry_points.txt
n8n_lint-1.1.2.dist-info/top_level.txt
n8n_lint-1.1.2.dist-info/RECORD
