Metadata-Version: 2.4
Name: n8n-lint
Version: 1.1.2
Summary: Lint your n8n JSON here.
Author-email: Dom Capparelli <web@Capparelli.ie>
Maintainer-email: Dom Capparelli <web@Capparelli.ie>
License-Expression: MIT
Project-URL: bugs, https://github.com/capp3/n8n_lint/issues
Project-URL: changelog, https://github.com/capp3/n8n_lint/blob/master/changelog.md
Project-URL: homepage, https://github.com/capp3/n8n_lint
Classifier: Development Status :: 5 - Production/Stable
Classifier: Intended Audience :: Developers
Classifier: Operating System :: OS Independent
Classifier: Programming Language :: Python :: 3
Classifier: Programming Language :: Python :: 3.12
Classifier: Programming Language :: Python :: 3.13
Classifier: Topic :: Software Development :: Quality Assurance
Classifier: Topic :: Software Development :: Testing
Requires-Python: >=3.12
License-File: LICENSE
Requires-Dist: typer>=0.12.0
Requires-Dist: rich>=13.0.0
Requires-Dist: jsonschema>=4.0.0
Dynamic: license-file
